ipymolstar/__init__.py
ipymolstar/molviewspec.py
ipymolstar/pdbemolstar.py
ipymolstar/panel/__init__.py
ipymolstar/panel/pdbemolstar.py
ipymolstar/static/molviewspec.css
ipymolstar/static/molviewspec.js
ipymolstar/static/pdbe-dark.css
ipymolstar/static/pdbe-light.css
ipymolstar/static/pdbemolstar.js
ipymolstar-0.1.0.dist-info/METADATA
ipymolstar-0.1.0.dist-info/WHEEL
ipymolstar-0.1.0.dist-info/licenses/LICENSE
ipymolstar-0.1.0.dist-info/RECORD
