Metadata-Version: 2.4
Name: ipymolstar
Version: 0.1.0
Summary: PDBeMolstar as anywidget
License: MIT License
License-File: LICENSE
Keywords: anywidget,molstar
Requires-Dist: anywidget
